Metadata-Version: 2.1
Name: fcscore
Version: 0.0.1
Summary: An API for automatic judging of precision aerobatics
Home-page: https://github.com/PyFlightCoach/FCScoreServer
Author: Thomas David
Author-email: thomasdavid0@gmail.com
